typetool/__init__.py
typetool/base_models.py
typetool/functions.py
typetool/json_encoder.py
typetool/parser.py
typetool/protocols.py
typetool/type_hint.py
typetool/types.py
typetool-0.0.1.dist-info/WHEEL
typetool-0.0.1.dist-info/METADATA
typetool-0.0.1.dist-info/RECORD
