Metadata-Version: 2.1
Name: typetool
Version: 0.0.1
Summary: type tool for checking and parsing types
Author: Daniel Arantes
Author-email: arantesdv@me.com
Requires-Python: >=3.9,<4.0
Classifier: Programming Language :: Python :: 3
Classifier: Programming Language :: Python :: 3.10
Classifier: Programming Language :: Python :: 3.9
Requires-Dist: Unidecode (>=1.3.6,<2.0.0)
